{"nodes": [{"id": "d_ysm_smartformflow_frontend_components_ui_form_tsx", "label": "form.tsx", "file_type": "code", "source_file": "D:\\YSM\\SmartFormFlow\\frontend\\components\\ui\\form.tsx", "source_location": "L1"}], "edges": [{"source": "d_ysm_smartformflow_frontend_components_ui_form_tsx", "target": "react", "relation": "imports_from", "confidence": "EXTRACTED", "source_file": "D:\\YSM\\SmartFormFlow\\frontend\\components\\ui\\form.tsx", "source_location": "L3", "weight": 1.0}, {"source": "d_ysm_smartformflow_frontend_components_ui_form_tsx", "target": "react_label", "relation": "imports_from", "confidence": "EXTRACTED", "source_file": "D:\\YSM\\SmartFormFlow\\frontend\\components\\ui\\form.tsx", "source_location": "L4", "weight": 1.0}, {"source": "d_ysm_smartformflow_frontend_components_ui_form_tsx", "target": "react_slot", "relation": "imports_from", "confidence": "EXTRACTED", "source_file": "D:\\YSM\\SmartFormFlow\\frontend\\components\\ui\\form.tsx", "source_location": "L5", "weight": 1.0}, {"source": "d_ysm_smartformflow_frontend_components_ui_form_tsx", "target": "react_hook_form", "relation": "imports_from", "confidence": "EXTRACTED", "source_file": "D:\\YSM\\SmartFormFlow\\frontend\\components\\ui\\form.tsx", "source_location": "L6", "weight": 1.0}, {"source": "d_ysm_smartformflow_frontend_components_ui_form_tsx", "target": "utils", "relation": "imports_from", "confidence": "EXTRACTED", "source_file": "D:\\YSM\\SmartFormFlow\\frontend\\components\\ui\\form.tsx", "source_location": "L15", "weight": 1.0}, {"source": "d_ysm_smartformflow_frontend_components_ui_form_tsx", "target": "label", "relation": "imports_from", "confidence": "EXTRACTED", "source_file": "D:\\YSM\\SmartFormFlow\\frontend\\components\\ui\\form.tsx", "source_location": "L16", "weight": 1.0}], "raw_calls": []}