{"nodes": [{"id": "d_ysm_smartformflow_frontend_app_page_tsx", "label": "page.tsx", "file_type": "code", "source_file": "D:\\YSM\\SmartFormFlow\\frontend\\app\\page.tsx", "source_location": "L1"}, {"id": "page_rootpage", "label": "RootPage()", "file_type": "code", "source_file": "D:\\YSM\\SmartFormFlow\\frontend\\app\\page.tsx", "source_location": "L3"}], "edges": [{"source": "d_ysm_smartformflow_frontend_app_page_tsx", "target": "navigation", "relation": "imports_from", "confidence": "EXTRACTED", "source_file": "D:\\YSM\\SmartFormFlow\\frontend\\app\\page.tsx", "source_location": "L1", "weight": 1.0}, {"source": "d_ysm_smartformflow_frontend_app_page_tsx", "target": "page_rootpage", "relation": "contains", "confidence": "EXTRACTED", "source_file": "D:\\YSM\\SmartFormFlow\\frontend\\app\\page.tsx", "source_location": "L3", "weight": 1.0}], "raw_calls": [{"caller_nid": "page_rootpage", "callee": "redirect", "source_file": "D:\\YSM\\SmartFormFlow\\frontend\\app\\page.tsx", "source_location": "L4"}]}