{"nodes": [{"id": "d_ysm_smartformflow_backend_src_utils_jwt_ts", "label": "jwt.ts", "file_type": "code", "source_file": "D:\\YSM\\SmartFormFlow\\backend\\src\\utils\\jwt.ts", "source_location": "L1"}, {"id": "jwt_createaccesstoken", "label": "createAccessToken()", "file_type": "code", "source_file": "D:\\YSM\\SmartFormFlow\\backend\\src\\utils\\jwt.ts", "source_location": "L7"}, {"id": "jwt_createrefreshtoken", "label": "createRefreshToken()", "file_type": "code", "source_file": "D:\\YSM\\SmartFormFlow\\backend\\src\\utils\\jwt.ts", "source_location": "L13"}, {"id": "jwt_verifytoken", "label": "verifyToken()", "file_type": "code", "source_file": "D:\\YSM\\SmartFormFlow\\backend\\src\\utils\\jwt.ts", "source_location": "L19"}, {"id": "jwt_verifyrefreshtoken", "label": "verifyRefreshToken()", "file_type": "code", "source_file": "D:\\YSM\\SmartFormFlow\\backend\\src\\utils\\jwt.ts", "source_location": "L23"}], "edges": [{"source": "d_ysm_smartformflow_backend_src_utils_jwt_ts", "target": "jsonwebtoken", "relation": "imports_from", "confidence": "EXTRACTED", "source_file": "D:\\YSM\\SmartFormFlow\\backend\\src\\utils\\jwt.ts", "source_location": "L1", "weight": 1.0}, {"source": "d_ysm_smartformflow_backend_src_utils_jwt_ts", "target": "jwt_createaccesstoken", "relation": "contains", "confidence": "EXTRACTED", "source_file": "D:\\YSM\\SmartFormFlow\\backend\\src\\utils\\jwt.ts", "source_location": "L7", "weight": 1.0}, {"source": "d_ysm_smartformflow_backend_src_utils_jwt_ts", "target": "jwt_createrefreshtoken", "relation": "contains", "confidence": "EXTRACTED", "source_file": "D:\\YSM\\SmartFormFlow\\backend\\src\\utils\\jwt.ts", "source_location": "L13", "weight": 1.0}, {"source": "d_ysm_smartformflow_backend_src_utils_jwt_ts", "target": "jwt_verifytoken", "relation": "contains", "confidence": "EXTRACTED", "source_file": "D:\\YSM\\SmartFormFlow\\backend\\src\\utils\\jwt.ts", "source_location": "L19", "weight": 1.0}, {"source": "d_ysm_smartformflow_backend_src_utils_jwt_ts", "target": "jwt_verifyrefreshtoken", "relation": "contains", "confidence": "EXTRACTED", "source_file": "D:\\YSM\\SmartFormFlow\\backend\\src\\utils\\jwt.ts", "source_location": "L23", "weight": 1.0}], "raw_calls": [{"caller_nid": "jwt_createaccesstoken", "callee": "sign", "source_file": "D:\\YSM\\SmartFormFlow\\backend\\src\\utils\\jwt.ts", "source_location": "L8"}, {"caller_nid": "jwt_createrefreshtoken", "callee": "sign", "source_file": "D:\\YSM\\SmartFormFlow\\backend\\src\\utils\\jwt.ts", "source_location": "L14"}, {"caller_nid": "jwt_verifytoken", "callee": "verify", "source_file": "D:\\YSM\\SmartFormFlow\\backend\\src\\utils\\jwt.ts", "source_location": "L20"}, {"caller_nid": "jwt_verifyrefreshtoken", "callee": "verify", "source_file": "D:\\YSM\\SmartFormFlow\\backend\\src\\utils\\jwt.ts", "source_location": "L24"}]}