{"nodes": [{"id": "d_ysm_smartformflow_backend_src_providers_razorpay_provider_ts", "label": "razorpay.provider.ts", "file_type": "code", "source_file": "D:\\YSM\\SmartFormFlow\\backend\\src\\providers\\razorpay.provider.ts", "source_location": "L1"}, {"id": "razorpay_provider_razorpayprovider", "label": "RazorpayProvider", "file_type": "code", "source_file": "D:\\YSM\\SmartFormFlow\\backend\\src\\providers\\razorpay.provider.ts", "source_location": "L4"}, {"id": "razorpay_provider_razorpayprovider_constructor", "label": ".constructor()", "file_type": "code", "source_file": "D:\\YSM\\SmartFormFlow\\backend\\src\\providers\\razorpay.provider.ts", "source_location": "L10"}, {"id": "razorpay_provider_razorpayprovider_getpublickey", "label": ".getPublicKey()", "file_type": "code", "source_file": "D:\\YSM\\SmartFormFlow\\backend\\src\\providers\\razorpay.provider.ts", "source_location": "L24"}, {"id": "razorpay_provider_razorpayprovider_createorder", "label": ".createOrder()", "file_type": "code", "source_file": "D:\\YSM\\SmartFormFlow\\backend\\src\\providers\\razorpay.provider.ts", "source_location": "L28"}, {"id": "razorpay_provider_razorpayprovider_verifypaymentsignature", "label": ".verifyPaymentSignature()", "file_type": "code", "source_file": "D:\\YSM\\SmartFormFlow\\backend\\src\\providers\\razorpay.provider.ts", "source_location": "L52"}, {"id": "razorpay_provider_razorpayprovider_verifywebhooksignature", "label": ".verifyWebhookSignature()", "file_type": "code", "source_file": "D:\\YSM\\SmartFormFlow\\backend\\src\\providers\\razorpay.provider.ts", "source_location": "L74"}], "edges": [{"source": "d_ysm_smartformflow_backend_src_providers_razorpay_provider_ts", "target": "razorpay", "relation": "imports_from", "confidence": "EXTRACTED", "source_file": "D:\\YSM\\SmartFormFlow\\backend\\src\\providers\\razorpay.provider.ts", "source_location": "L1", "weight": 1.0}, {"source": "d_ysm_smartformflow_backend_src_providers_razorpay_provider_ts", "target": "crypto", "relation": "imports_from", "confidence": "EXTRACTED", "source_file": "D:\\YSM\\SmartFormFlow\\backend\\src\\providers\\razorpay.provider.ts", "source_location": "L2", "weight": 1.0}, {"source": "d_ysm_smartformflow_backend_src_providers_razorpay_provider_ts", "target": "razorpay_provider_razorpayprovider", "relation": "contains", "confidence": "EXTRACTED", "source_file": "D:\\YSM\\SmartFormFlow\\backend\\src\\providers\\razorpay.provider.ts", "source_location": "L4", "weight": 1.0}, {"source": "razorpay_provider_razorpayprovider", "target": "razorpay_provider_razorpayprovider_constructor", "relation": "method", "confidence": "EXTRACTED", "source_file": "D:\\YSM\\SmartFormFlow\\backend\\src\\providers\\razorpay.provider.ts", "source_location": "L10", "weight": 1.0}, {"source": "razorpay_provider_razorpayprovider", "target": "razorpay_provider_razorpayprovider_getpublickey", "relation": "method", "confidence": "EXTRACTED", "source_file": "D:\\YSM\\SmartFormFlow\\backend\\src\\providers\\razorpay.provider.ts", "source_location": "L24", "weight": 1.0}, {"source": "razorpay_provider_razorpayprovider", "target": "razorpay_provider_razorpayprovider_createorder", "relation": "method", "confidence": "EXTRACTED", "source_file": "D:\\YSM\\SmartFormFlow\\backend\\src\\providers\\razorpay.provider.ts", "source_location": "L28", "weight": 1.0}, {"source": "razorpay_provider_razorpayprovider", "target": "razorpay_provider_razorpayprovider_verifypaymentsignature", "relation": "method", "confidence": "EXTRACTED", "source_file": "D:\\YSM\\SmartFormFlow\\backend\\src\\providers\\razorpay.provider.ts", "source_location": "L52", "weight": 1.0}, {"source": "razorpay_provider_razorpayprovider", "target": "razorpay_provider_razorpayprovider_verifywebhooksignature", "relation": "method", "confidence": "EXTRACTED", "source_file": "D:\\YSM\\SmartFormFlow\\backend\\src\\providers\\razorpay.provider.ts", "source_location": "L74", "weight": 1.0}], "raw_calls": [{"caller_nid": "razorpay_provider_razorpayprovider_constructor", "callee": "trim", "source_file": "D:\\YSM\\SmartFormFlow\\backend\\src\\providers\\razorpay.provider.ts", "source_location": "L13"}, {"caller_nid": "razorpay_provider_razorpayprovider_constructor", "callee": "trim", "source_file": "D:\\YSM\\SmartFormFlow\\backend\\src\\providers\\razorpay.provider.ts", "source_location": "L14"}, {"caller_nid": "razorpay_provider_razorpayprovider_constructor", "callee": "trim", "source_file": "D:\\YSM\\SmartFormFlow\\backend\\src\\providers\\razorpay.provider.ts", "source_location": "L18"}, {"caller_nid": "razorpay_provider_razorpayprovider_createorder", "callee": "create", "source_file": "D:\\YSM\\SmartFormFlow\\backend\\src\\providers\\razorpay.provider.ts", "source_location": "L35"}, {"caller_nid": "razorpay_provider_razorpayprovider_verifypaymentsignature", "callee": "digest", "source_file": "D:\\YSM\\SmartFormFlow\\backend\\src\\providers\\razorpay.provider.ts", "source_location": "L60"}, {"caller_nid": "razorpay_provider_razorpayprovider_verifypaymentsignature", "callee": "update", "source_file": "D:\\YSM\\SmartFormFlow\\backend\\src\\providers\\razorpay.provider.ts", "source_location": "L60"}, {"caller_nid": "razorpay_provider_razorpayprovider_verifypaymentsignature", "callee": "createHmac", "source_file": "D:\\YSM\\SmartFormFlow\\backend\\src\\providers\\razorpay.provider.ts", "source_location": "L60"}, {"caller_nid": "razorpay_provider_razorpayprovider_verifypaymentsignature", "callee": "timingSafeEqual", "source_file": "D:\\YSM\\SmartFormFlow\\backend\\src\\providers\\razorpay.provider.ts", "source_location": "L65"}, {"caller_nid": "razorpay_provider_razorpayprovider_verifypaymentsignature", "callee": "from", "source_file": "D:\\YSM\\SmartFormFlow\\backend\\src\\providers\\razorpay.provider.ts", "source_location": "L66"}, {"caller_nid": "razorpay_provider_razorpayprovider_verifypaymentsignature", "callee": "from", "source_file": "D:\\YSM\\SmartFormFlow\\backend\\src\\providers\\razorpay.provider.ts", "source_location": "L67"}, {"caller_nid": "razorpay_provider_razorpayprovider_verifywebhooksignature", "callee": "digest", "source_file": "D:\\YSM\\SmartFormFlow\\backend\\src\\providers\\razorpay.provider.ts", "source_location": "L78"}, {"caller_nid": "razorpay_provider_razorpayprovider_verifywebhooksignature", "callee": "update", "source_file": "D:\\YSM\\SmartFormFlow\\backend\\src\\providers\\razorpay.provider.ts", "source_location": "L78"}, {"caller_nid": "razorpay_provider_razorpayprovider_verifywebhooksignature", "callee": "createHmac", "source_file": "D:\\YSM\\SmartFormFlow\\backend\\src\\providers\\razorpay.provider.ts", "source_location": "L78"}]}