{"nodes": [{"id": "d_ysm_smartformflow_backend_src_repositories_payment_repo_ts", "label": "payment.repo.ts", "file_type": "code", "source_file": "D:\\YSM\\SmartFormFlow\\backend\\src\\repositories\\payment.repo.ts", "source_location": "L1"}, {"id": "payment_repo_paymentrepository", "label": "PaymentRepository", "file_type": "code", "source_file": "D:\\YSM\\SmartFormFlow\\backend\\src\\repositories\\payment.repo.ts", "source_location": "L63"}, {"id": "payment_repo_paymentrepository_create", "label": ".create()", "file_type": "code", "source_file": "D:\\YSM\\SmartFormFlow\\backend\\src\\repositories\\payment.repo.ts", "source_location": "L65"}, {"id": "payment_repo_paymentrepository_findbysubmissionid", "label": ".findBySubmissionId()", "file_type": "code", "source_file": "D:\\YSM\\SmartFormFlow\\backend\\src\\repositories\\payment.repo.ts", "source_location": "L86"}, {"id": "payment_repo_paymentrepository_findbyid", "label": ".findById()", "file_type": "code", "source_file": "D:\\YSM\\SmartFormFlow\\backend\\src\\repositories\\payment.repo.ts", "source_location": "L92"}, {"id": "payment_repo_paymentrepository_findbyrazorpayorderid", "label": ".findByRazorpayOrderId()", "file_type": "code", "source_file": "D:\\YSM\\SmartFormFlow\\backend\\src\\repositories\\payment.repo.ts", "source_location": "L98"}, {"id": "payment_repo_paymentrepository_findbyrazorpaypaymentid", "label": ".findByRazorpayPaymentId()", "file_type": "code", "source_file": "D:\\YSM\\SmartFormFlow\\backend\\src\\repositories\\payment.repo.ts", "source_location": "L106"}, {"id": "payment_repo_paymentrepository_markpending", "label": ".markPending()", "file_type": "code", "source_file": "D:\\YSM\\SmartFormFlow\\backend\\src\\repositories\\payment.repo.ts", "source_location": "L114"}, {"id": "payment_repo_paymentrepository_marksuccess", "label": ".markSuccess()", "file_type": "code", "source_file": "D:\\YSM\\SmartFormFlow\\backend\\src\\repositories\\payment.repo.ts", "source_location": "L126"}, {"id": "payment_repo_paymentrepository_markfailed", "label": ".markFailed()", "file_type": "code", "source_file": "D:\\YSM\\SmartFormFlow\\backend\\src\\repositories\\payment.repo.ts", "source_location": "L141"}, {"id": "payment_repo_paymentrepository_markcancelled", "label": ".markCancelled()", "file_type": "code", "source_file": "D:\\YSM\\SmartFormFlow\\backend\\src\\repositories\\payment.repo.ts", "source_location": "L156"}, {"id": "payment_repo_paymentrepository_findbyeventid", "label": ".findByEventId()", "file_type": "code", "source_file": "D:\\YSM\\SmartFormFlow\\backend\\src\\repositories\\payment.repo.ts", "source_location": "L165"}, {"id": "payment_repo_paymentrepository_findbyeventidpaginated", "label": ".findByEventIdPaginated()", "file_type": "code", "source_file": "D:\\YSM\\SmartFormFlow\\backend\\src\\repositories\\payment.repo.ts", "source_location": "L172"}, {"id": "payment_repo_paymentrepository_updateforretry", "label": ".updateForRetry()", "file_type": "code", "source_file": "D:\\YSM\\SmartFormFlow\\backend\\src\\repositories\\payment.repo.ts", "source_location": "L198"}, {"id": "payment_repo_paymentrepository_allpayments", "label": ".allPayments()", "file_type": "code", "source_file": "D:\\YSM\\SmartFormFlow\\backend\\src\\repositories\\payment.repo.ts", "source_location": "L213"}], "edges": [{"source": "d_ysm_smartformflow_backend_src_repositories_payment_repo_ts", "target": "client", "relation": "imports_from", "confidence": "EXTRACTED", "source_file": "D:\\YSM\\SmartFormFlow\\backend\\src\\repositories\\payment.repo.ts", "source_location": "L1", "weight": 1.0}, {"source": "d_ysm_smartformflow_backend_src_repositories_payment_repo_ts", "target": "d_ysm_smartformflow_backend_src_config_db", "relation": "imports_from", "confidence": "EXTRACTED", "source_file": "D:\\YSM\\SmartFormFlow\\backend\\src\\repositories\\payment.repo.ts", "source_location": "L2", "weight": 1.0}, {"source": "d_ysm_smartformflow_backend_src_repositories_payment_repo_ts", "target": "payment_repo_paymentrepository", "relation": "contains", "confidence": "EXTRACTED", "source_file": "D:\\YSM\\SmartFormFlow\\backend\\src\\repositories\\payment.repo.ts", "source_location": "L63", "weight": 1.0}, {"source": "payment_repo_paymentrepository", "target": "payment_repo_paymentrepository_create", "relation": "method", "confidence": "EXTRACTED", "source_file": "D:\\YSM\\SmartFormFlow\\backend\\src\\repositories\\payment.repo.ts", "source_location": "L65", "weight": 1.0}, {"source": "payment_repo_paymentrepository", "target": "payment_repo_paymentrepository_findbysubmissionid", "relation": "method", "confidence": "EXTRACTED", "source_file": "D:\\YSM\\SmartFormFlow\\backend\\src\\repositories\\payment.repo.ts", "source_location": "L86", "weight": 1.0}, {"source": "payment_repo_paymentrepository", "target": "payment_repo_paymentrepository_findbyid", "relation": "method", "confidence": "EXTRACTED", "source_file": "D:\\YSM\\SmartFormFlow\\backend\\src\\repositories\\payment.repo.ts", "source_location": "L92", "weight": 1.0}, {"source": "payment_repo_paymentrepository", "target": "payment_repo_paymentrepository_findbyrazorpayorderid", "relation": "method", "confidence": "EXTRACTED", "source_file": "D:\\YSM\\SmartFormFlow\\backend\\src\\repositories\\payment.repo.ts", "source_location": "L98", "weight": 1.0}, {"source": "payment_repo_paymentrepository", "target": "payment_repo_paymentrepository_findbyrazorpaypaymentid", "relation": "method", "confidence": "EXTRACTED", "source_file": "D:\\YSM\\SmartFormFlow\\backend\\src\\repositories\\payment.repo.ts", "source_location": "L106", "weight": 1.0}, {"source": "payment_repo_paymentrepository", "target": "payment_repo_paymentrepository_markpending", "relation": "method", "confidence": "EXTRACTED", "source_file": "D:\\YSM\\SmartFormFlow\\backend\\src\\repositories\\payment.repo.ts", "source_location": "L114", "weight": 1.0}, {"source": "payment_repo_paymentrepository", "target": "payment_repo_paymentrepository_marksuccess", "relation": "method", "confidence": "EXTRACTED", "source_file": "D:\\YSM\\SmartFormFlow\\backend\\src\\repositories\\payment.repo.ts", "source_location": "L126", "weight": 1.0}, {"source": "payment_repo_paymentrepository", "target": "payment_repo_paymentrepository_markfailed", "relation": "method", "confidence": "EXTRACTED", "source_file": "D:\\YSM\\SmartFormFlow\\backend\\src\\repositories\\payment.repo.ts", "source_location": "L141", "weight": 1.0}, {"source": "payment_repo_paymentrepository", "target": "payment_repo_paymentrepository_markcancelled", "relation": "method", "confidence": "EXTRACTED", "source_file": "D:\\YSM\\SmartFormFlow\\backend\\src\\repositories\\payment.repo.ts", "source_location": "L156", "weight": 1.0}, {"source": "payment_repo_paymentrepository", "target": "payment_repo_paymentrepository_findbyeventid", "relation": "method", "confidence": "EXTRACTED", "source_file": "D:\\YSM\\SmartFormFlow\\backend\\src\\repositories\\payment.repo.ts", "source_location": "L165", "weight": 1.0}, {"source": "payment_repo_paymentrepository", "target": "payment_repo_paymentrepository_findbyeventidpaginated", "relation": "method", "confidence": "EXTRACTED", "source_file": "D:\\YSM\\SmartFormFlow\\backend\\src\\repositories\\payment.repo.ts", "source_location": "L172", "weight": 1.0}, {"source": "payment_repo_paymentrepository", "target": "payment_repo_paymentrepository_updateforretry", "relation": "method", "confidence": "EXTRACTED", "source_file": "D:\\YSM\\SmartFormFlow\\backend\\src\\repositories\\payment.repo.ts", "source_location": "L198", "weight": 1.0}, {"source": "payment_repo_paymentrepository", "target": "payment_repo_paymentrepository_allpayments", "relation": "method", "confidence": "EXTRACTED", "source_file": "D:\\YSM\\SmartFormFlow\\backend\\src\\repositories\\payment.repo.ts", "source_location": "L213", "weight": 1.0}], "raw_calls": [{"caller_nid": "payment_repo_paymentrepository_findbysubmissionid", "callee": "findUnique", "source_file": "D:\\YSM\\SmartFormFlow\\backend\\src\\repositories\\payment.repo.ts", "source_location": "L87"}, {"caller_nid": "payment_repo_paymentrepository_findbyid", "callee": "findUnique", "source_file": "D:\\YSM\\SmartFormFlow\\backend\\src\\repositories\\payment.repo.ts", "source_location": "L93"}, {"caller_nid": "payment_repo_paymentrepository_findbyrazorpayorderid", "callee": "findUnique", "source_file": "D:\\YSM\\SmartFormFlow\\backend\\src\\repositories\\payment.repo.ts", "source_location": "L99"}, {"caller_nid": "payment_repo_paymentrepository_findbyrazorpaypaymentid", "callee": "findUnique", "source_file": "D:\\YSM\\SmartFormFlow\\backend\\src\\repositories\\payment.repo.ts", "source_location": "L107"}, {"caller_nid": "payment_repo_paymentrepository_markpending", "callee": "update", "source_file": "D:\\YSM\\SmartFormFlow\\backend\\src\\repositories\\payment.repo.ts", "source_location": "L115"}, {"caller_nid": "payment_repo_paymentrepository_marksuccess", "callee": "update", "source_file": "D:\\YSM\\SmartFormFlow\\backend\\src\\repositories\\payment.repo.ts", "source_location": "L127"}, {"caller_nid": "payment_repo_paymentrepository_markfailed", "callee": "update", "source_file": "D:\\YSM\\SmartFormFlow\\backend\\src\\repositories\\payment.repo.ts", "source_location": "L142"}, {"caller_nid": "payment_repo_paymentrepository_markcancelled", "callee": "update", "source_file": "D:\\YSM\\SmartFormFlow\\backend\\src\\repositories\\payment.repo.ts", "source_location": "L157"}, {"caller_nid": "payment_repo_paymentrepository_findbyeventid", "callee": "findMany", "source_file": "D:\\YSM\\SmartFormFlow\\backend\\src\\repositories\\payment.repo.ts", "source_location": "L166"}, {"caller_nid": "payment_repo_paymentrepository_findbyeventidpaginated", "callee": "findMany", "source_file": "D:\\YSM\\SmartFormFlow\\backend\\src\\repositories\\payment.repo.ts", "source_location": "L178"}, {"caller_nid": "payment_repo_paymentrepository_findbyeventidpaginated", "callee": "pop", "source_file": "D:\\YSM\\SmartFormFlow\\backend\\src\\repositories\\payment.repo.ts", "source_location": "L191"}, {"caller_nid": "payment_repo_paymentrepository_updateforretry", "callee": "update", "source_file": "D:\\YSM\\SmartFormFlow\\backend\\src\\repositories\\payment.repo.ts", "source_location": "L202"}, {"caller_nid": "payment_repo_paymentrepository_allpayments", "callee": "findMany", "source_file": "D:\\YSM\\SmartFormFlow\\backend\\src\\repositories\\payment.repo.ts", "source_location": "L222"}, {"caller_nid": "payment_repo_paymentrepository_allpayments", "callee": "pop", "source_file": "D:\\YSM\\SmartFormFlow\\backend\\src\\repositories\\payment.repo.ts", "source_location": "L237"}]}